{
  "nodes": [
    {
      "parameters": {
        "rule": {
          "interval": [
            {
              "field": "hours",
              "hoursInterval": 8
            }
          ]
        }
      },
      "type": "n8n-nodes-base.scheduleTrigger",
      "typeVersion": 1.2,
      "position": [
        7280,
        1792
      ],
      "id": "0b32b621-556f-488d-af7b-9158efb35baa",
      "name": "Every 8 Hours"
    },
    {
      "parameters": {
        "documentId": {
          "__rl": true,
          "value": "1m-CxKMnfImceMJL1Fzv98jbVz6a9bGqqhy6ekPI-Cac",
          "mode": "list",
          "cachedResultName": "ðŸš©8-hour Retries",
          "cachedResultUrl": "https://docs.google.com/spreadsheets/d/1m-CxKMnfImceMJL1Fzv98jbVz6a9bGqqhy6ekPI-Cac/edit?usp=drivesdk"
        },
        "sheetName": {
          "__rl": true,
          "value": "gid=0",
          "mode": "list",
          "cachedResultName": "FailedItems",
          "cachedResultUrl": "https://docs.google.com/spreadsheets/d/1m-CxKMnfImceMJL1Fzv98jbVz6a9bGqqhy6ekPI-Cac/edit#gid=0"
        },
        "options": {}
      },
      "type": "n8n-nodes-base.googleSheets",
      "typeVersion": 4,
      "position": [
        7520,
        1792
      ],
      "id": "02ab8c65-2ddc-42ba-a95d-d85b0e8abf62",
      "name": "Read FailedItems",
      "credentials": {
        "googleSheetsOAuth2Api": {
          "id": "O03W9YZyCWUacxnv",
          "name": "GoogleDriveMAIN"
        }
      }
    },
    {
      "parameters": {
        "conditions": {
          "options": {
            "version": 2,
            "combinator": "and"
          },
          "conditions": [
            {
              "leftValue": "={{ $json.status }}",
              "rightValue": "pending_retry",
              "operator": {
                "type": "string",
                "operation": "equals"
              }
            },
            {
              "leftValue": "={{ $json.is_retryable }}",
              "rightValue": "true",
              "operator": {
                "type": "string",
                "operation": "equals"
              }
            }
          ]
        },
        "options": {}
      },
      "type": "n8n-nodes-base.filter",
      "typeVersion": 2.2,
      "position": [
        7760,
        1792
      ],
      "id": "49422025-05b0-43e3-9b25-44e7f874ece2",
      "name": "Filter Retryable"
    },
    {
      "parameters": {
        "options": {}
      },
      "type": "n8n-nodes-base.splitInBatches",
      "typeVersion": 3,
      "position": [
        8000,
        1792
      ],
      "id": "bec87bea-1edb-4dad-9131-d59eb21b8a56",
      "name": "Loop Over Items"
    },
    {
      "parameters": {
        "conditions": {
          "options": {
            "version": 2,
            "combinator": "and"
          },
          "conditions": [
            {
              "leftValue": "={{ Number($json.retry_count) }}",
              "rightValue": 3,
              "operator": {
                "type": "number",
                "operation": "lt"
              }
            }
          ]
        },
        "options": {}
      },
      "type": "n8n-nodes-base.if",
      "typeVersion": 2.2,
      "position": [
        8240,
        1792
      ],
      "id": "fea74f4a-14d4-4fa8-8e10-1e69c23ff865",
      "name": "retry_count < 3?"
    },
    {
      "parameters": {
        "method": "POST",
        "url": "=https://primary-production-2e961.up.railway.app/api/v1/executions/{{ $json.execution_id }}/retry",
        "authentication": "genericCredentialType",
        "genericAuthType": "httpHeaderAuth",
        "options": {
          "response": {
            "response": {
              "neverError": true
            }
          }
        }
      },
      "type": "n8n-nodes-base.httpRequest",
      "typeVersion": 4.2,
      "position": [
        8480,
        1696
      ],
      "id": "b22c5b55-0bf9-4f73-8b2e-c3833aefc0f9",
      "name": "Execute Retry via API",
      "credentials": {
        "httpHeaderAuth": {
          "id": "vjEcFZksIjUCKNRz",
          "name": "Header Auth account"
        }
      }
    },
    {
      "parameters": {
        "jsCode": "// Check Retry Result\n// Determines if the API retry call succeeded\n\nconst item = $('Loop Over Items').item.json;\nconst apiResponse = $json;\nconst newRetryCount = Number(item.retry_count || 0) + 1;\n\n// Check if API call succeeded (status 200 and got new execution ID)\nconst retrySuccess = apiResponse.data?.id ? true : false;\n\nreturn [{\n  json: {\n    ...item,\n    retry_count: newRetryCount,\n    last_retry_at: new Date().toISOString(),\n    retry_success: retrySuccess,\n    new_execution_id: apiResponse.data?.id || null\n  }\n}];"
      },
      "type": "n8n-nodes-base.code",
      "typeVersion": 2,
      "position": [
        8880,
        1696
      ],
      "id": "99cba8d8-bacc-4a57-8894-acd2c7d2da8b",
      "name": "Check Retry Result"
    },
    {
      "parameters": {
        "operation": "update",
        "documentId": {
          "__rl": true,
          "value": "1m-CxKMnfImceMJL1Fzv98jbVz6a9bGqqhy6ekPI-Cac",
          "mode": "list",
          "cachedResultName": "ðŸš©8-hour Retries",
          "cachedResultUrl": "https://docs.google.com/spreadsheets/d/1m-CxKMnfImceMJL1Fzv98jbVz6a9bGqqhy6ekPI-Cac/edit?usp=drivesdk"
        },
        "sheetName": {
          "__rl": true,
          "value": "gid=0",
          "mode": "list",
          "cachedResultName": "FailedItems",
          "cachedResultUrl": "https://docs.google.com/spreadsheets/d/1m-CxKMnfImceMJL1Fzv98jbVz6a9bGqqhy6ekPI-Cac/edit#gid=0"
        },
        "columns": {
          "mappingMode": "defineBelow",
          "value": {
            "execution_id": "={{ $json.execution_id }}",
            "retry_count": "={{ $json.retry_count }}",
            "status": "={{ $json.retry_success ? 'resolved' : 'pending_retry' }}"
          },
          "matchingColumns": [
            "execution_id"
          ],
          "schema": [
            {
              "id": "execution_id",
              "displayName": "execution_id",
              "required": false,
              "defaultMatch": true,
              "display": true,
              "type": "string",
              "canBeUsedToMatch": true
            },
            {
              "id": "retry_count",
              "displayName": "retry_count",
              "required": false,
              "defaultMatch": false,
              "display": true,
              "type": "string",
              "canBeUsedToMatch": true
            },
            {
              "id": "status",
              "displayName": "status",
              "required": false,
              "defaultMatch": false,
              "display": true,
              "type": "string",
              "canBeUsedToMatch": true
            }
          ]
        },
        "options": {}
      },
      "type": "n8n-nodes-base.googleSheets",
      "typeVersion": 4,
      "position": [
        9120,
        1696
      ],
      "id": "d352f53f-4afc-40e7-b0bd-941893addc4f",
      "name": "Update Retry Count",
      "credentials": {
        "googleSheetsOAuth2Api": {
          "id": "O03W9YZyCWUacxnv",
          "name": "GoogleDriveMAIN"
        }
      }
    },
    {
      "parameters": {
        "jsCode": "// Mark as escalated - requires human intervention\nconst item = $json;\n\nreturn [{\n  json: {\n    ...item,\n    status: 'escalated',\n    escalated_at: new Date().toISOString()\n  }\n}];"
      },
      "type": "n8n-nodes-base.code",
      "typeVersion": 2,
      "position": [
        8480,
        1904
      ],
      "id": "e3002ff4-cf40-4f2f-ab3c-2515f65b6f8d",
      "name": "Mark Escalated"
    },
    {
      "parameters": {
        "operation": "update",
        "documentId": {
          "__rl": true,
          "value": "1m-CxKMnfImceMJL1Fzv98jbVz6a9bGqqhy6ekPI-Cac",
          "mode": "list",
          "cachedResultName": "ðŸš©8-hour Retries",
          "cachedResultUrl": "https://docs.google.com/spreadsheets/d/1m-CxKMnfImceMJL1Fzv98jbVz6a9bGqqhy6ekPI-Cac/edit?usp=drivesdk"
        },
        "sheetName": {
          "__rl": true,
          "value": "gid=0",
          "mode": "list",
          "cachedResultName": "FailedItems",
          "cachedResultUrl": "https://docs.google.com/spreadsheets/d/1m-CxKMnfImceMJL1Fzv98jbVz6a9bGqqhy6ekPI-Cac/edit#gid=0"
        },
        "columns": {
          "mappingMode": "defineBelow",
          "value": {
            "status": "={{ $json.status }}"
          },
          "matchingColumns": [
            "execution_id"
          ],
          "schema": [
            {
              "id": "execution_id",
              "displayName": "execution_id",
              "required": false,
              "defaultMatch": true,
              "display": true,
              "type": "string",
              "canBeUsedToMatch": true
            },
            {
              "id": "status",
              "displayName": "status",
              "required": false,
              "defaultMatch": false,
              "display": true,
              "type": "string",
              "canBeUsedToMatch": true
            }
          ]
        },
        "options": {}
      },
      "type": "n8n-nodes-base.googleSheets",
      "typeVersion": 4,
      "position": [
        8720,
        1904
      ],
      "id": "b9e8de8a-4417-41d3-96ee-484419cff5d7",
      "name": "Update Status Escalated",
      "credentials": {
        "googleSheetsOAuth2Api": {
          "id": "O03W9YZyCWUacxnv",
          "name": "GoogleDriveMAIN"
        }
      }
    },
    {
      "parameters": {
        "chatId": "7582730035",
        "text": "=ðŸš¨ ESCALATION: 3 retries exhausted\n\nWorkflow: {{ $json.workflow_name }}\nNode: {{ $json.failed_node }}\nError: {{ $json.error_message }}\n\nExecution ID: {{ $json.execution_id }}\nError Type: {{ $json.error_type }}\n\nâš ï¸ Manual intervention required",
        "additionalFields": {
          "appendAttribution": false
        }
      },
      "type": "n8n-nodes-base.telegram",
      "typeVersion": 1.2,
      "position": [
        8960,
        1904
      ],
      "id": "d50a8f12-d797-4c73-90fb-45263973c4f5",
      "name": "Alert: Escalation",
      "webhookId": "7d7cb033-297e-4132-9a85-1dcb7e81273f",
      "credentials": {
        "telegramApi": {
          "id": "mlZdNwRkWhIVuDdr",
          "name": "Telegram inbox_important"
        }
      }
    },
    {
      "parameters": {
        "content": "## 8-hour Task Resolver\n\n**Purpose:** Auto-retry failed workflow executions logged in FailedItems sheet.\n\n**Flow:**\n1. Every 8 hours, read pending retryable items\n2. For each item with retry_count < 3:\n   - Call n8n API retry endpoint\n   - Check result and update retry_count in sheet\n   - If success â†’ status='resolved'\n3. For items with retry_count >= 3:\n   - Mark as 'escalated'\n   - Send Telegram alert for human intervention\n\n**n8n API Retry:**\nUses POST /api/v1/executions/{id}/retry to re-run original execution.\nPreserves original trigger data (e.g., Gmail message).\nNo need to pass inputs - n8n handles context automatically.",
        "height": 380,
        "width": 360
      },
      "type": "n8n-nodes-base.stickyNote",
      "typeVersion": 1,
      "position": [
        7280,
        1392
      ],
      "id": "ffeba6ed-40e6-4449-9427-acc26c973c1f",
      "name": "Overview"
    },
    {
      "parameters": {
        "content": "### Escalation Path\nretry_count >= 3\nâ†’ Human intervention required",
        "height": 120,
        "width": 280
      },
      "type": "n8n-nodes-base.stickyNote",
      "typeVersion": 1,
      "position": [
        8480,
        2016
      ],
      "id": "1e2357b2-63f1-4535-8620-59115cbd379b",
      "name": "Escalation Note"
    },
    {
      "parameters": {
        "content": "### Retry Path\nretry_count < 3\nâ†’ Execute Retry via API â†’ Check result â†’ Update sheet",
        "height": 120,
        "width": 280
      },
      "type": "n8n-nodes-base.stickyNote",
      "typeVersion": 1,
      "position": [
        8480,
        1520
      ],
      "id": "8a0f4b77-74d4-441c-88be-e4835691c52c",
      "name": "Retry Note"
    }
  ],
  "connections": {
    "Every 8 Hours": {
      "main": [
        [
          {
            "node": "Read FailedItems",
            "type": "main",
            "index": 0
          }
        ]
      ]
    },
    "Read FailedItems": {
      "main": [
        [
          {
            "node": "Filter Retryable",
            "type": "main",
            "index": 0
          }
        ]
      ]
    },
    "Filter Retryable": {
      "main": [
        [
          {
            "node": "Loop Over Items",
            "type": "main",
            "index": 0
          }
        ]
      ]
    },
    "Loop Over Items": {
      "main": [
        [],
        [
          {
            "node": "retry_count < 3?",
            "type": "main",
            "index": 0
          }
        ]
      ]
    },
    "retry_count < 3?": {
      "main": [
        [
          {
            "node": "Execute Retry via API",
            "type": "main",
            "index": 0
          }
        ],
        [
          {
            "node": "Mark Escalated",
            "type": "main",
            "index": 0
          }
        ]
      ]
    },
    "Execute Retry via API": {
      "main": [
        [
          {
            "node": "Check Retry Result",
            "type": "main",
            "index": 0
          }
        ]
      ]
    },
    "Check Retry Result": {
      "main": [
        [
          {
            "node": "Update Retry Count",
            "type": "main",
            "index": 0
          }
        ]
      ]
    },
    "Update Retry Count": {
      "main": [
        [
          {
            "node": "Loop Over Items",
            "type": "main",
            "index": 0
          }
        ]
      ]
    },
    "Mark Escalated": {
      "main": [
        [
          {
            "node": "Update Status Escalated",
            "type": "main",
            "index": 0
          }
        ]
      ]
    },
    "Update Status Escalated": {
      "main": [
        [
          {
            "node": "Alert: Escalation",
            "type": "main",
            "index": 0
          }
        ]
      ]
    },
    "Alert: Escalation": {
      "main": [
        [
          {
            "node": "Loop Over Items",
            "type": "main",
            "index": 0
          }
        ]
      ]
    }
  },
  "pinData": {},
  "meta": {
    "instanceId": "09a80676641fdc883fcaa67648f06322bebbd00adb281b1cf481107091bcc026"
  }
}